iuliia/__init__.py
iuliia/__main__.py
iuliia/engine.py
iuliia/mapping.py
iuliia/schema.py
iuliia/schemas.py
iuliia/schemas/LICENSE
iuliia/schemas/README.md
iuliia/schemas/ala_lc.json
iuliia/schemas/ala_lc_alt.json
iuliia/schemas/bgn_pcgn.json
iuliia/schemas/bgn_pcgn_alt.json
iuliia/schemas/bs_2979.json
iuliia/schemas/bs_2979_alt.json
iuliia/schemas/gost_16876.json
iuliia/schemas/gost_16876_alt.json
iuliia/schemas/gost_52290.json
iuliia/schemas/gost_52535.json
iuliia/schemas/gost_7034.json
iuliia/schemas/gost_779.json
iuliia/schemas/gost_779_alt.json
iuliia/schemas/icao_doc_9303.json
iuliia/schemas/iso_9_1954.json
iuliia/schemas/iso_9_1968.json
iuliia/schemas/iso_9_1968_alt.json
iuliia/schemas/mosmetro.json
iuliia/schemas/mvd_310.json
iuliia/schemas/mvd_310_fr.json
iuliia/schemas/mvd_782.json
iuliia/schemas/schema.jsd
iuliia/schemas/scientific.json
iuliia/schemas/telegram.json
iuliia/schemas/ungegn_1987.json
iuliia/schemas/uz.json
iuliia/schemas/wikipedia.json
iuliia/schemas/yandex_maps.json
iuliia/schemas/yandex_money.json
iuliia-0.12.0.dist-info/entry_points.txt
iuliia-0.12.0.dist-info/LICENSE
iuliia-0.12.0.dist-info/WHEEL
iuliia-0.12.0.dist-info/METADATA
iuliia-0.12.0.dist-info/RECORD
