Metadata-Version: 2.3
Name: iuliia
Version: 0.12.0
Summary: Transliterate Cyrillic → Latin in every possible way
Keywords: transliteration,cyrillic,latin,romanization
Author-email: Anton Zhiyanov <m@antonz.ru>
Requires-Python: >=3.10
Classifier: License :: OSI Approved :: MIT License
Classifier: Programming Language :: Python :: 3
Project-URL: Source, https://github.com/nalgeon/iuliia-py
